DESCRIPTION.rst
MANIFEST.in
commit-version
setup.py
UniversalAnalytics/HTTPLog.py
UniversalAnalytics/Tracker.py
UniversalAnalytics/__init__.py
test/test_everything.py
universal_analytics_python.egg-info/PKG-INFO
universal_analytics_python.egg-info/SOURCES.txt
universal_analytics_python.egg-info/dependency_links.txt
universal_analytics_python.egg-info/top_level.txt
universal_analytics_python.egg-info/zip-safe