Metadata-Version: 1.1
Name: universal-analytics-python
Version: 0.2.4
Summary: Universal Analytics Python Module
Home-page: https://github.com/analytics-pros/universal-analytics-python
Author: Sam Briesemeister
Author-email: opensource@analyticspros.com
License: BSD
Download-URL: https://github.com/analytics-pros/universal-analytics-python/tarball/0.2.4
Platform: UNKNOWN
